[
    {
        "inputs": [
            {
                "internalType": "string",
                "name": "",
                "type": "string"
            },
            {
                "internalType": "uint256",
                "name": "",
                "type": "uint256"
            }
        ],
        "name": "Farmers_map",
        "outputs": [
            {
                "internalType": "uint256",
                "name": "",
                "type": "uint256"
            }
        ],
        "stateMutability": "view",
        "type": "function"
    },
    {
        "inputs": [
            {
                "internalType": "string",
                "name": "_fid",
                "type": "string"
            },
            {
                "internalType": "uint256",
                "name": "_UPIN",
                "type": "uint256"
            },
            {
                "internalType": "string",
                "name": "_landTitle",
                "type": "string"
            },
            {
                "internalType": "uint64",
                "name": "_SurvayNo",
                "type": "uint64"
            },
            {
                "internalType": "string",
                "name": "_area",
                "type": "string"
            },
            {
                "internalType": "string",
                "name": "_landUse",
                "type": "string"
            }
        ],
        "name": "add_land",
        "outputs": [],
        "stateMutability": "nonpayable",
        "type": "function"
    },
    {
        "inputs": [
            {
                "internalType": "uint256",
                "name": "",
                "type": "uint256"
            }
        ],
        "name": "farmer",
        "outputs": [
            {
                "internalType": "uint256",
                "name": "UPIN",
                "type": "uint256"
            },
            {
                "internalType": "string",
                "name": "landTitle",
                "type": "string"
            },
            {
                "internalType": "uint64",
                "name": "SurvayNo",
                "type": "uint64"
            },
            {
                "internalType": "string",
                "name": "area",
                "type": "string"
            },
            {
                "internalType": "string",
                "name": "landUse",
                "type": "string"
            }
        ],
        "stateMutability": "view",
        "type": "function"
    },
    {
        "inputs": [
            {
                "internalType": "string",
                "name": "a",
                "type": "string"
            }
        ],
        "name": "farmers_arr_add",
        "outputs": [],
        "stateMutability": "nonpayable",
        "type": "function"
    },
    {
        "inputs": [],
        "name": "getAllFarmers",
        "outputs": [
            {
                "internalType": "string[]",
                "name": "",
                "type": "string[]"
            }
        ],
        "stateMutability": "view",
        "type": "function"
    },
    {
        "inputs": [
            {
                "internalType": "string",
                "name": "_fid",
                "type": "string"
            }
        ],
        "name": "getFarmersLand",
        "outputs": [
            {
                "internalType": "uint256[]",
                "name": "",
                "type": "uint256[]"
            }
        ],
        "stateMutability": "nonpayable",
        "type": "function"
    },
    {
        "inputs": [
            {
                "internalType": "string",
                "name": "_fid",
                "type": "string"
            },
            {
                "internalType": "uint256",
                "name": "_UPIN",
                "type": "uint256"
            }
        ],
        "name": "getFarmersLands",
        "outputs": [
            {
                "components": [
                    {
                        "internalType": "uint256",
                        "name": "UPIN",
                        "type": "uint256"
                    },
                    {
                        "internalType": "string",
                        "name": "landTitle",
                        "type": "string"
                    },
                    {
                        "internalType": "uint64",
                        "name": "SurvayNo",
                        "type": "uint64"
                    },
                    {
                        "internalType": "string",
                        "name": "area",
                        "type": "string"
                    },
                    {
                        "internalType": "string",
                        "name": "landUse",
                        "type": "string"
                    }
                ],
                "internalType": "struct SimpleStorage.Land",
                "name": "",
                "type": "tuple"
            }
        ],
        "stateMutability": "nonpayable",
        "type": "function"
    },
    {
        "inputs": [
            {
                "internalType": "string",
                "name": "_buyer_fid",
                "type": "string"
            },
            {
                "internalType": "string",
                "name": "_seller_fid",
                "type": "string"
            },
            {
                "internalType": "uint256",
                "name": "_UPIN",
                "type": "uint256"
            }
        ],
        "name": "sell_land",
        "outputs": [],
        "stateMutability": "nonpayable",
        "type": "function"
    },
    {
        "inputs": [
            {
                "internalType": "uint256",
                "name": "",
                "type": "uint256"
            }
        ],
        "name": "upin_to_land",
        "outputs": [
            {
                "internalType": "uint256",
                "name": "UPIN",
                "type": "uint256"
            },
            {
                "internalType": "string",
                "name": "landTitle",
                "type": "string"
            },
            {
                "internalType": "uint64",
                "name": "SurvayNo",
                "type": "uint64"
            },
            {
                "internalType": "string",
                "name": "area",
                "type": "string"
            },
            {
                "internalType": "string",
                "name": "landUse",
                "type": "string"
            }
        ],
        "stateMutability": "view",
        "type": "function"
    }
]
